LICENSE
MANIFEST.in
README.md
pyproject.toml
setup.py
ks_digital_twin/__init__.py
ks_digital_twin/py.typed
ks_digital_twin/requirements-dev.txt
ks_digital_twin/requirements.txt
ks_digital_twin.egg-info/PKG-INFO
ks_digital_twin.egg-info/SOURCES.txt
ks_digital_twin.egg-info/dependency_links.txt
ks_digital_twin.egg-info/requires.txt
ks_digital_twin.egg-info/top_level.txt
ks_digital_twin/actor/__init__.py
ks_digital_twin/actor/base.py
ks_digital_twin/actor/keyboard.py
ks_digital_twin/actor/pykos_bot.py
ks_digital_twin/actor/sinusoid.py
ks_digital_twin/models/__init__.py
ks_digital_twin/puppet/__init__.py
ks_digital_twin/puppet/base.py
ks_digital_twin/puppet/mujoco_puppet.py
ks_digital_twin/puppet/pybullet_puppet.py
tests/test_dummy.py