Metadata-Version: 2.2
Name: ks_digital_twin
Version: 0.0.3
Summary: The digital_twin project
Home-page: https://github.com/kscalelabs/digital-twin
Author: Benjamin Bolte
Requires-Python: >=3.11
License-File: LICENSE
Requires-Dist: colorlogging
Requires-Dist: kscale
Requires-Dist: pykos
Requires-Dist: pynput
Requires-Dist: numpy
Provides-Extra: dev
Requires-Dist: black; extra == "dev"
Requires-Dist: darglint; extra == "dev"
Requires-Dist: mypy; extra == "dev"
Requires-Dist: pytest; extra == "dev"
Requires-Dist: ruff; extra == "dev"
Dynamic: author
Dynamic: description
Dynamic: description-content-type
Dynamic: home-page
Dynamic: provides-extra
Dynamic: requires-dist
Dynamic: requires-python
Dynamic: summary
